pyelabdata/__init__.py
pyelabdata/pyelabdata.py
pyelabdata-0.2.10.dist-info/LICENSE
pyelabdata-0.2.10.dist-info/METADATA
pyelabdata-0.2.10.dist-info/WHEEL
pyelabdata-0.2.10.dist-info/top_level.txt
pyelabdata-0.2.10.dist-info/RECORD
