Metadata-Version: 2.2
Name: pyelabdata
Version: 0.2.10
Summary: pyelabdata provides functions for simple one-line access to data in eLabFTW
Author-email: "Elektronikpraktikum, Department Physik, FAU Erlangen-Nürnberg" <physik-ep@fau.de>, "Michael Krieger, Lehrstuhl für Angewandte Physik, FAU Erlangen-Nürnberg" <michael.krieger@fau.de>
Project-URL: Repository, https://github.com/FAU-PHYSIK-EP/pyelabdata
Project-URL: Issues, https://github.com/FAU-PHYSIK-EP/pyelabdata/issues
Classifier: Programming Language :: Python :: 3
Classifier: License :: OSI Approved :: MIT License
Classifier: Operating System :: OS Independent
Requires-Python: >=3.8
License-File: LICENSE
Requires-Dist: numpy
Requires-Dist: elabapi_python
Requires-Dist: pandas
Requires-Dist: h5py
Requires-Dist: matplotlib
Requires-Dist: pathlib
Requires-Dist: datetime
Requires-Dist: ipylab
Requires-Dist: asyncio
Requires-Dist: lxml
Requires-Dist: python-dotenv
